LICENSE
README.md
pyproject.toml
setup.cfg
setup.py
treeno/__init__.py
treeno/base.py
treeno/cli.py
treeno/expression.py
treeno/groupby.py
treeno/orderby.py
treeno/printer.py
treeno/relation.py
treeno/util.py
treeno/visitor.py
treeno/window.py
treeno.egg-info/PKG-INFO
treeno.egg-info/SOURCES.txt
treeno.egg-info/dependency_links.txt
treeno.egg-info/entry_points.txt
treeno.egg-info/requires.txt
treeno.egg-info/top_level.txt
treeno/builder/__init__.py
treeno/builder/convert.py
treeno/datatypes/__init__.py
treeno/datatypes/builder.py
treeno/datatypes/conversions.py
treeno/datatypes/inference.py
treeno/datatypes/resolve.py
treeno/datatypes/types.py
treeno/functions/__init__.py
treeno/functions/aggregate.py
treeno/functions/base.py
treeno/functions/common.py
treeno/functions/conditional.py
treeno/functions/datetime.py
treeno/functions/math.py
treeno/functions/session.py
treeno/functions/string.py
treeno/grammar/SqlBase.g4
treeno/grammar/__init__.py
treeno/grammar/parse.py
treeno/grammar/gen/SqlBaseLexer.py
treeno/grammar/gen/SqlBaseListener.py
treeno/grammar/gen/SqlBaseParser.py
treeno/grammar/gen/SqlBaseVisitor.py
treeno/grammar/gen/__init__.py