Metadata-Version: 2.1
Name: treeno
Version: 0.3.368
Summary: Trino SQL building library
Home-page: https://github.com/OneRaynyDay/treeno/tree/main/treeno
Author: Ray Zhang
Author-email: peifeng2005@gmail.com
License: MIT License
Keywords: trino, sql, python
Platform: UNKNOWN
Classifier: Development Status :: 2 - Pre-Alpha
Classifier: Intended Audience :: Developers
Classifier: License :: OSI Approved :: MIT License
Classifier: Operating System :: OS Independent
Classifier: Programming Language :: Python
Classifier: Programming Language :: Python :: 3 :: Only
Classifier: Programming Language :: Python :: 3.6
Classifier: Programming Language :: Python :: 3.7
Classifier: Programming Language :: Python :: 3.8
Classifier: Programming Language :: Python :: 3.9
Classifier: Programming Language :: Python :: 3.10
Requires-Python: >=3.6
Provides-Extra: test
Provides-Extra: docs
